{
  "protocol_version" : "0.0.6",
  "configuration" : {
    "version" : "(6.12.0.113) (2020-02/4fdfb5b1fd5)",
    "tlc" : "normal",
    "sigsgev" : "altstack",
    "notifications" : "kqueue",
    "architecture" : "amd64",
    "disabled_features" : "none",
    "smallconfig" : "disabled",
    "bigarrays" : "disabled",
    "softdebug" : "enabled",
    "interpreter" : "enabled",
    "llvm_support" : "0",
    "suspend" : "hybrid"
  },
  "memory" : {
    "Resident Size" : "139730944",
    "Virtual Size" : "4704305152",
    "minor_gc_time" : "0",
    "major_gc_time" : "0",
    "minor_gc_count" : "0",
    "major_gc_count" : "0",
    "major_gc_time_concurrent" : "0"
 },
  "threads" : [
 {
    "is_managed" : false,
    "offset_free_hash" : "0x0",
    "offset_rich_hash" : "0x0",
    "crashed" : false,
    "native_thread_id" : "0x70000bfee000",
    "thread_info_addr" : "0x7f882d02c000",
    "thread_name" : "Finalizer",
    "ctx" : {
      "IP" : "0x7fff67c69e36",
      "SP" : "0x70000bfedeb8",
      "BP" : "0x70000bfedf00"
  },
    "unmanaged_frames" : [
  {
      "is_managed" : "false",
      "native_address" : "0x10733ca06",
      "native_offset" : "0x00000"
   }
,
  {
      "is_managed" : "false",
      "native_address" : "0x1074d8165",
      "native_offset" : "0x00000"
   }
,
  {
      "is_managed" : "false",
      "native_address" : "0x1074d7e97",
      "native_offset" : "0x00000"
   }
,
  {
      "is_managed" : "false",
      "native_address" : "0x1073a89d0",
      "native_offset" : "0x00000"
   }
,
  {
      "is_managed" : "false",
      "native_address" : "0x7fff67d215fd",
      "native_offset" : "0x00000"
   }
,
  {
      "is_managed" : "false",
      "native_address" : "unregistered"
   }
,
  {
      "is_managed" : "false",
      "native_address" : "0x1074d8dad",
      "native_offset" : "0x00000"
   }
,
  {
      "is_managed" : "false",
      "native_address" : "0x7fff67d2d109",
      "native_offset" : "0x00000"
   }
,
  {
      "is_managed" : "false",
      "native_address" : "0x7fff67d28b8b",
      "native_offset" : "0x00000"
   }

  ]
 },
 {
    "is_managed" : false,
    "offset_free_hash" : "0x0",
    "offset_rich_hash" : "0x0",
    "crashed" : false,
    "native_thread_id" : "0x1162a5dc0",
    "thread_info_addr" : "0x7f882a80a000",
    "thread_name" : "tid_307",
    "ctx" : {
      "IP" : "0x7fff67c6c882",
      "SP" : "0x7ffee8973bf8",
      "BP" : "0x7ffee8973c90"
  },
    "unmanaged_frames" : [
  {
      "is_managed" : "false",
      "native_address" : "0x10733ca06",
      "native_offset" : "0x00000"
   }
,
  {
      "is_managed" : "false",
      "native_address" : "0x1074d8165",
      "native_offset" : "0x00000"
   }
,
  {
      "is_managed" : "false",
      "native_address" : "0x1074d7e97",
      "native_offset" : "0x00000"
   }
,
  {
      "is_managed" : "false",
      "native_address" : "0x1073a89d0",
      "native_offset" : "0x00000"
   }
,
  {
      "is_managed" : "false",
      "native_address" : "0x7fff67d215fd",
      "native_offset" : "0x00000"
   }
,
  {
      "is_managed" : "false",
      "native_address" : "unregistered"
   }
,
  {
      "is_managed" : "false",
      "native_address" : "0x107572ee0",
      "native_offset" : "0x00000"
   }
,
  {
      "is_managed" : "false",
      "native_address" : "0x10758afc1",
      "native_offset" : "0x00000"
   }
,
  {
      "is_managed" : "false",
      "native_address" : "0x1074d5084",
      "native_offset" : "0x00000"
   }
,
  {
      "is_managed" : "false",
      "native_address" : "0x1074d4e8a",
      "native_offset" : "0x00000"
   }
,
  {
      "is_managed" : "false",
      "native_address" : "0x1073020fa",
      "native_offset" : "0x00000"
   }
,
  {
      "is_managed" : "false",
      "native_address" : "0x10728e1e8",
      "native_offset" : "0x00000"
   }
,
  {
      "is_managed" : "false",
      "native_address" : "0x7fff67b28cc9",
      "native_offset" : "0x00000"
   }

  ]
 },
 {
    "is_managed" : true,
    "offset_free_hash" : "0x11a6748113",
    "offset_rich_hash" : "0x11a6748628",
    "crashed" : true,
    "native_thread_id" : "0x70000e36a000",
    "thread_info_addr" : "0x7f882d258a00",
    "thread_name" : "tid_6303",
    "ctx" : {
      "IP" : "0x7fff67c7033a",
      "SP" : "0x70000e362b98",
      "BP" : "0x70000e362bc0"
  },
    "managed_frames" : [
  {
      "is_managed" : "false",
      "native_address" : "unregistered"
   }
,
  {
      "is_managed" : "true",
      "guid" : "58E88B8B-C383-4E07-A237-B0C4D21C89F2",
      "token" : "0x00000",
      "native_offset" : "0x0",
      "filename" : "mscorlib.dll",
      "sizeofimage" : "0x472000",
      "timestamp" : "0x86058d7a",
      "il_offset" : "0x00000"
   }
,
  {
      "is_managed" : "true",
      "guid" : "58E88B8B-C383-4E07-A237-B0C4D21C89F2",
      "token" : "0x00000",
      "native_offset" : "0x0",
      "filename" : "mscorlib.dll",
      "sizeofimage" : "0x472000",
      "timestamp" : "0x86058d7a",
      "il_offset" : "0x00015"
   }
,
  {
      "is_managed" : "true",
      "guid" : "181E198A-F674-4D54-82D2-31B9E17B3F9B",
      "token" : "0x6004287",
      "native_offset" : "0x0",
      "filename" : "System.dll",
      "sizeofimage" : "0x292000",
      "timestamp" : "0xc58d4017",
      "il_offset" : "0x0026a"
   }
,
  {
      "is_managed" : "true",
      "guid" : "181E198A-F674-4D54-82D2-31B9E17B3F9B",
      "token" : "0x6004487",
      "native_offset" : "0x0",
      "filename" : "System.dll",
      "sizeofimage" : "0x292000",
      "timestamp" : "0xc58d4017",
      "il_offset" : "0x00043"
   }
,
  {
      "is_managed" : "true",
      "guid" : "58E88B8B-C383-4E07-A237-B0C4D21C89F2",
      "token" : "0x6001ed4",
      "native_offset" : "0x0",
      "filename" : "mscorlib.dll",
      "sizeofimage" : "0x472000",
      "timestamp" : "0x86058d7a",
      "il_offset" : "0x00071"
   }
,
  {
      "is_managed" : "true",
      "guid" : "58E88B8B-C383-4E07-A237-B0C4D21C89F2",
      "token" : "0x6001ed2",
      "native_offset" : "0x0",
      "filename" : "mscorlib.dll",
      "sizeofimage" : "0x472000",
      "timestamp" : "0x86058d7a",
      "il_offset" : "0x00000"
   }
,
  {
      "is_managed" : "true",
      "guid" : "58E88B8B-C383-4E07-A237-B0C4D21C89F2",
      "token" : "0x6001ed1",
      "native_offset" : "0x0",
      "filename" : "mscorlib.dll",
      "sizeofimage" : "0x472000",
      "timestamp" : "0x86058d7a",
      "il_offset" : "0x0002b"
   }
,
  {
      "is_managed" : "true",
      "guid" : "181E198A-F674-4D54-82D2-31B9E17B3F9B",
      "token" : "0x6004286",
      "native_offset" : "0x0",
      "filename" : "System.dll",
      "sizeofimage" : "0x292000",
      "timestamp" : "0xc58d4017",
      "il_offset" : "0x00093"
   }
,
  {
      "is_managed" : "true",
      "guid" : "181E198A-F674-4D54-82D2-31B9E17B3F9B",
      "token" : "0x00000",
      "native_offset" : "0x0",
      "filename" : "System.dll",
      "sizeofimage" : "0x292000",
      "timestamp" : "0xc58d4017",
      "il_offset" : "0xffffffff"
   }
,
  {
      "is_managed" : "false",
      "native_address" : "unregistered"
   }
,
  {
      "is_managed" : "true",
      "guid" : "181E198A-F674-4D54-82D2-31B9E17B3F9B",
      "token" : "0x00000",
      "native_offset" : "0x0",
      "filename" : "System.dll",
      "sizeofimage" : "0x292000",
      "timestamp" : "0xc58d4017",
      "il_offset" : "0x00000"
   }
,
  {
      "is_managed" : "true",
      "guid" : "181E198A-F674-4D54-82D2-31B9E17B3F9B",
      "token" : "0x600447f",
      "native_offset" : "0x0",
      "filename" : "System.dll",
      "sizeofimage" : "0x292000",
      "timestamp" : "0xc58d4017",
      "il_offset" : "0x0003a"
   }
,
  {
      "is_managed" : "true",
      "guid" : "58E88B8B-C383-4E07-A237-B0C4D21C89F2",
      "token" : "0x6001f2c",
      "native_offset" : "0x0",
      "filename" : "mscorlib.dll",
      "sizeofimage" : "0x472000",
      "timestamp" : "0x86058d7a",
      "il_offset" : "0x00025"
   }
,
  {
      "is_managed" : "true",
      "guid" : "58E88B8B-C383-4E07-A237-B0C4D21C89F2",
      "token" : "0x6001ed4",
      "native_offset" : "0x0",
      "filename" : "mscorlib.dll",
      "sizeofimage" : "0x472000",
      "timestamp" : "0x86058d7a",
      "il_offset" : "0x00071"
   }
,
  {
      "is_managed" : "true",
      "guid" : "58E88B8B-C383-4E07-A237-B0C4D21C89F2",
      "token" : "0x6001ed2",
      "native_offset" : "0x0",
      "filename" : "mscorlib.dll",
      "sizeofimage" : "0x472000",
      "timestamp" : "0x86058d7a",
      "il_offset" : "0x00000"
   }
,
  {
      "is_managed" : "true",
      "guid" : "58E88B8B-C383-4E07-A237-B0C4D21C89F2",
      "token" : "0x6001ed1",
      "native_offset" : "0x0",
      "filename" : "mscorlib.dll",
      "sizeofimage" : "0x472000",
      "timestamp" : "0x86058d7a",
      "il_offset" : "0x0002b"
   }
,
  {
      "is_managed" : "true",
      "guid" : "58E88B8B-C383-4E07-A237-B0C4D21C89F2",
      "token" : "0x00000",
      "native_offset" : "0x0",
      "filename" : "mscorlib.dll",
      "sizeofimage" : "0x472000",
      "timestamp" : "0x86058d7a",
      "il_offset" : "0x0002a"
   }

  ],
  "unmanaged_frames" : [
 {
    "is_managed" : "false",
    "native_address" : "0x10733ca06",
    "native_offset" : "0x00000"
  }
,
 {
    "is_managed" : "false",
    "native_address" : "0x1074d8165",
    "native_offset" : "0x00000"
  }
,
 {
    "is_managed" : "false",
    "native_address" : "0x1074d87da",
    "native_offset" : "0x00000"
  }
,
 {
    "is_managed" : "false",
    "native_address" : "0x1073a9a97",
    "native_offset" : "0x00000"
  }
,
 {
    "is_managed" : "false",
    "native_address" : "0x10734169e",
    "native_offset" : "0x00000"
  }
,
 {
    "is_managed" : "false",
    "native_address" : "0x1073a8d8f",
    "native_offset" : "0x00000"
  }
,
 {
    "is_managed" : "false",
    "native_address" : "0x7fff67d215fd",
    "native_offset" : "0x00000"
  }
,
 {
    "is_managed" : "false",
    "native_address" : "unregistered"
  }
,
 {
    "is_managed" : "false",
    "native_address" : "0x7fff67bf7808",
    "native_offset" : "0x00000"
  }
,
 {
    "is_managed" : "false",
    "native_address" : "0x107595f67",
    "native_offset" : "0x00000"
  }
,
 {
    "is_managed" : "false",
    "native_address" : "0x107576def",
    "native_offset" : "0x00000"
  }
,
 {
    "is_managed" : "false",
    "native_address" : "0x1075963fe",
    "native_offset" : "0x00000"
  }
,
 {
    "is_managed" : "false",
    "native_address" : "0x10759657f",
    "native_offset" : "0x00000"
  }
,
 {
    "is_managed" : "false",
    "native_address" : "0x1075965ba",
    "native_offset" : "0x00000"
  }
,
 {
    "is_managed" : "false",
    "native_address" : "0x10758ad8e",
    "native_offset" : "0x00000"
  }
,
 {
    "is_managed" : "false",
    "native_address" : "0x1074d26d1",
    "native_offset" : "0x00000"
  }
,
 {
    "is_managed" : "false",
    "native_address" : "0x1074d934d",
    "native_offset" : "0x00000"
  }
,
 {
    "is_managed" : "false",
    "native_address" : "0x1074d6fbc",
    "native_offset" : "0x00000"
  }
,
 {
    "is_managed" : "true",
    "guid" : "58E88B8B-C383-4E07-A237-B0C4D21C89F2",
    "token" : "0x00000",
    "native_offset" : "0x0",
    "filename" : "mscorlib.dll",
    "sizeofimage" : "0x472000",
    "timestamp" : "0x86058d7a",
    "il_offset" : "0x00000"
  }
,
 {
    "is_managed" : "true",
    "guid" : "58E88B8B-C383-4E07-A237-B0C4D21C89F2",
    "token" : "0x00000",
    "native_offset" : "0x0",
    "filename" : "mscorlib.dll",
    "sizeofimage" : "0x472000",
    "timestamp" : "0x86058d7a",
    "il_offset" : "0x00000"
  }
,
 {
    "is_managed" : "true",
    "guid" : "181E198A-F674-4D54-82D2-31B9E17B3F9B",
    "token" : "0x6004287",
    "native_offset" : "0x0",
    "filename" : "System.dll",
    "sizeofimage" : "0x292000",
    "timestamp" : "0xc58d4017",
    "il_offset" : "0x00000"
  }
,
 {
    "is_managed" : "true",
    "guid" : "181E198A-F674-4D54-82D2-31B9E17B3F9B",
    "token" : "0x6004487",
    "native_offset" : "0x0",
    "filename" : "System.dll",
    "sizeofimage" : "0x292000",
    "timestamp" : "0xc58d4017",
    "il_offset" : "0x00000"
  }
,
 {
    "is_managed" : "true",
    "guid" : "58E88B8B-C383-4E07-A237-B0C4D21C89F2",
    "token" : "0x6001ed4",
    "native_offset" : "0x0",
    "filename" : "mscorlib.dll",
    "sizeofimage" : "0x472000",
    "timestamp" : "0x86058d7a",
    "il_offset" : "0x00000"
  }
,
 {
    "is_managed" : "true",
    "guid" : "58E88B8B-C383-4E07-A237-B0C4D21C89F2",
    "token" : "0x6001ed2",
    "native_offset" : "0x0",
    "filename" : "mscorlib.dll",
    "sizeofimage" : "0x472000",
    "timestamp" : "0x86058d7a",
    "il_offset" : "0x00000"
  }
,
 {
    "is_managed" : "true",
    "guid" : "181E198A-F674-4D54-82D2-31B9E17B3F9B",
    "token" : "0x00000",
    "native_offset" : "0x0",
    "filename" : "System.dll",
    "sizeofimage" : "0x292000",
    "timestamp" : "0xc58d4017",
    "il_offset" : "0x00000"
  }
,
 {
    "is_managed" : "false",
    "native_address" : "0x7fff2f196993",
    "native_offset" : "0x00000"
  }
,
 {
    "is_managed" : "false",
    "native_address" : "0x7fff2f195dfe",
    "native_offset" : "0x00000"
  }
,
 {
    "is_managed" : "false",
    "native_address" : "0x7fff2f195cf7",
    "native_offset" : "0x00000"
  }
,
 {
    "is_managed" : "false",
    "native_address" : "0x7fff2f19892b",
    "native_offset" : "0x00000"
  }
,
 {
    "is_managed" : "false",
    "native_address" : "0x7fff2daa7b05",
    "native_offset" : "0x00000"
  }
,
 {
    "is_managed" : "false",
    "native_address" : "0x7fff2da79304",
    "native_offset" : "0x00000"
  }
,
 {
    "is_managed" : "false",
    "native_address" : "0x7fff2da79250",
    "native_offset" : "0x00000"
  }
,
 {
    "is_managed" : "false",
    "native_address" : "0x7fff2da77d79",
    "native_offset" : "0x00000"
  }
,
 {
    "is_managed" : "false",
    "native_address" : "0x7fff2da76e3e",
    "native_offset" : "0x00000"
  }
,
 {
    "is_managed" : "false",
    "native_address" : "0x7fff2daff489",
    "native_offset" : "0x00000"
  }
,
 {
    "is_managed" : "false",
    "native_address" : "0x10e1fdfcc",
    "native_offset" : "0x00000"
  }
,
 {
    "is_managed" : "true",
    "guid" : "181E198A-F674-4D54-82D2-31B9E17B3F9B",
    "token" : "0x00000",
    "native_offset" : "0x0",
    "filename" : "System.dll",
    "sizeofimage" : "0x292000",
    "timestamp" : "0xc58d4017",
    "il_offset" : "0x00000"
  }
,
 {
    "is_managed" : "true",
    "guid" : "181E198A-F674-4D54-82D2-31B9E17B3F9B",
    "token" : "0x600447f",
    "native_offset" : "0x0",
    "filename" : "System.dll",
    "sizeofimage" : "0x292000",
    "timestamp" : "0xc58d4017",
    "il_offset" : "0x00000"
  }
,
 {
    "is_managed" : "true",
    "guid" : "58E88B8B-C383-4E07-A237-B0C4D21C89F2",
    "token" : "0x6001f2c",
    "native_offset" : "0x0",
    "filename" : "mscorlib.dll",
    "sizeofimage" : "0x472000",
    "timestamp" : "0x86058d7a",
    "il_offset" : "0x00000"
  }
,
 {
    "is_managed" : "true",
    "guid" : "58E88B8B-C383-4E07-A237-B0C4D21C89F2",
    "token" : "0x6001ed2",
    "native_offset" : "0x0",
    "filename" : "mscorlib.dll",
    "sizeofimage" : "0x472000",
    "timestamp" : "0x86058d7a",
    "il_offset" : "0x00000"
  }
,
 {
    "is_managed" : "false",
    "native_address" : "0x10729e9d2",
    "native_offset" : "0x00000"
  }
,
 {
    "is_managed" : "false",
    "native_address" : "0x1074adf97",
    "native_offset" : "0x00000"
  }
,
 {
    "is_managed" : "false",
    "native_address" : "0x1074b4840",
    "native_offset" : "0x00000"
  }
,
 {
    "is_managed" : "false",
    "native_address" : "0x1074d8ded",
    "native_offset" : "0x00000"
  }
,
 {
    "is_managed" : "false",
    "native_address" : "0x7fff67d2d109",
    "native_offset" : "0x00000"
  }
,
 {
    "is_managed" : "false",
    "native_address" : "0x7fff67d28b8b",
    "native_offset" : "0x00000"
  }

 ]
}
]
}